{
  "default": {
    "id": "3",
    "network": "main",
    "name": "华南(成都)",
    "rpc": "http://140.143.83.98:8545",
    "web": "http://sero-cash.gitee.io/pullup"
  },
  "host": [
    {
      "id": "1",
      "network": "main",
      "name": "华南(成都)",
      "rpc": "http://140.143.83.98:8545",
      "web": "http://sero-cash.gitee.io/pullup"
    },
    {
      "id": "2",
      "network": "main",
      "name": "华南(广州)",
      "rpc": "http://129.204.197.105:8545",
      "web": "http://sero-cash.gitee.io/pullup"
    },
    {
      "id": "3",
      "network": "main",
      "name": "JAPAN",
      "rpc": "http://52.199.145.159:8545",
      "web": "http://sero-cash.gitee.io/pullup"
    }
  ]
}